Eridu/__init__.py
Eridu/labs/MCD.py
Eridu/labs/__init__.py
eridu_data_generator-0.1.0.dist-info/licenses/LICENSE
eridu_data_generator-0.1.0.dist-info/METADATA
eridu_data_generator-0.1.0.dist-info/WHEEL
eridu_data_generator-0.1.0.dist-info/top_level.txt
eridu_data_generator-0.1.0.dist-info/RECORD
