Metadata-Version: 2.4
Name: eridu-data-generator
Version: 0.1.0
Summary: A mock cloud financial data generator.
Author-email: Your Name <your@email.com>
Requires-Python: >=3.7
License-File: LICENSE
Requires-Dist: pandas
Requires-Dist: numpy
Dynamic: license-file
